LICENSE
MANIFEST.in
README.md
requirements.txt
setup.cfg
setup.py
cache_it/__init__.py
cache_it/test_cache_it.py
cache_it/test_init_cache.py
cache_it.egg-info/PKG-INFO
cache_it.egg-info/SOURCES.txt
cache_it.egg-info/dependency_links.txt
cache_it.egg-info/requires.txt
cache_it.egg-info/top_level.txt