Metadata-Version: 1.1
Name: cache-it
Version: 0.0.1
Summary: Decorators for caching
Home-page: http://github.com/shoz/cache_it
Author: Shoji Ihara
Author-email: shoji.ihara@gmail.com
License: switchcache
